[
  {
    "inputs": [
      {
        "internalType": "string",
        "name": "panelId",
        "type": "string"
      },
      {
        "internalType": "string",
        "name": "eventType",
        "type": "string"
      },
      {
        "internalType": "bytes32",
        "name": "eventHash",
        "type": "bytes32"
      }
    ],
    "name": "addPanelEvent",
    "outputs": [],
    "stateMutability": "nonpayable",
    "type": "function"
  },
  {
    "inputs": [
      {
        "internalType": "address",
        "name": "_oracleFinal",
        "type": "address"
      }
    ],
    "stateMutability": "nonpayable",
    "type": "constructor"
  },
  {
    "anonymous": false,
    "inputs": [
      {
        "indexed": false,
        "internalType": "address",
        "name": "oldAdmin",
        "type": "address"
      },
      {
        "indexed": false,
        "internalType": "address",
        "name": "newAdmin",
        "type": "address"
      }
    ],
    "name": "AdminChanged",
    "type": "event"
  },
  {
    "inputs": [
      {
        "internalType": "address",
        "name": "newAdmin",
        "type": "address"
      }
    ],
    "name": "changeAdmin",
    "outputs": [],
    "stateMutability": "nonpayable",
    "type": "function"
  },
  {
    "anonymous": false,
    "inputs": [
      {
        "indexed": false,
        "internalType": "string",
        "name": "panelId",
        "type": "string"
      },
      {
        "indexed": false,
        "internalType": "string",
        "name": "eventType",
        "type": "string"
      },
      {
        "indexed": false,
        "internalType": "bytes32",
        "name": "eventHash",
        "type": "bytes32"
      },
      {
        "indexed": false,
        "internalType": "address",
        "name": "validatedBy",
        "type": "address"
      },
      {
        "indexed": false,
        "internalType": "uint256",
        "name": "timestamp",
        "type": "uint256"
      }
    ],
    "name": "PanelEventAdded",
    "type": "event"
  },
  {
    "anonymous": false,
    "inputs": [
      {
        "indexed": false,
        "internalType": "string",
        "name": "panelId",
        "type": "string"
      },
      {
        "indexed": false,
        "internalType": "bytes32",
        "name": "factoryHash",
        "type": "bytes32"
      },
      {
        "indexed": false,
        "internalType": "uint256",
        "name": "timestamp",
        "type": "uint256"
      }
    ],
    "name": "PanelRegistered",
    "type": "event"
  },
  {
    "inputs": [
      {
        "internalType": "string",
        "name": "panelId",
        "type": "string"
      },
      {
        "internalType": "bytes32",
        "name": "hash",
        "type": "bytes32"
      }
    ],
    "name": "registerPanel",
    "outputs": [],
    "stateMutability": "nonpayable",
    "type": "function"
  },
  {
    "inputs": [
      {
        "internalType": "string",
        "name": "panelId",
        "type": "string"
      }
    ],
    "name": "getEventCount",
    "outputs": [
      {
        "internalType": "uint256",
        "name": "",
        "type": "uint256"
      }
    ],
    "stateMutability": "view",
    "type": "function"
  },
  {
    "inputs": [
      {
        "internalType": "string",
        "name": "panelId",
        "type": "string"
      },
      {
        "internalType": "uint256",
        "name": "index",
        "type": "uint256"
      }
    ],
    "name": "getPanelEvent",
    "outputs": [
      {
        "internalType": "string",
        "name": "eventType",
        "type": "string"
      },
      {
        "internalType": "bytes32",
        "name": "eventHash",
        "type": "bytes32"
      },
      {
        "internalType": "address",
        "name": "validatedBy",
        "type": "address"
      },
      {
        "internalType": "uint256",
        "name": "timestamp",
        "type": "uint256"
      }
    ],
    "stateMutability": "view",
    "type": "function"
  },
  {
    "inputs": [],
    "name": "oracleFinal",
    "outputs": [
      {
        "internalType": "address",
        "name": "",
        "type": "address"
      }
    ],
    "stateMutability": "view",
    "type": "function"
  },
  {
    "inputs": [
      {
        "internalType": "string",
        "name": "",
        "type": "string"
      },
      {
        "internalType": "uint256",
        "name": "",
        "type": "uint256"
      }
    ],
    "name": "panelEvents",
    "outputs": [
      {
        "internalType": "string",
        "name": "eventType",
        "type": "string"
      },
      {
        "internalType": "bytes32",
        "name": "eventHash",
        "type": "bytes32"
      },
      {
        "internalType": "address",
        "name": "validatedBy",
        "type": "address"
      },
      {
        "internalType": "uint256",
        "name": "timestamp",
        "type": "uint256"
      }
    ],
    "stateMutability": "view",
    "type": "function"
  },
  {
    "inputs": [
      {
        "internalType": "string",
        "name": "",
        "type": "string"
      }
    ],
    "name": "panels",
    "outputs": [
      {
        "internalType": "bytes32",
        "name": "factoryHash",
        "type": "bytes32"
      },
      {
        "internalType": "uint256",
        "name": "timestamp",
        "type": "uint256"
      },
      {
        "internalType": "address",
        "name": "registeredBy",
        "type": "address"
      }
    ],
    "stateMutability": "view",
    "type": "function"
  },
  {
    "inputs": [],
    "name": "platformAdmin",
    "outputs": [
      {
        "internalType": "address",
        "name": "",
        "type": "address"
      }
    ],
    "stateMutability": "view",
    "type": "function"
  }
]
